packaging_tutorial_hatch_dhylton/__about__.py
packaging_tutorial_hatch_dhylton/__init__.py
packaging_tutorial_hatch_dhylton/example.py
packaging_tutorial_hatch_dhylton-0.0.1.dist-info/METADATA
packaging_tutorial_hatch_dhylton-0.0.1.dist-info/WHEEL
packaging_tutorial_hatch_dhylton-0.0.1.dist-info/licenses/LICENSE.txt
packaging_tutorial_hatch_dhylton-0.0.1.dist-info/RECORD
